<?xml version="1.0" encoding="UTF-8" standalone="yes"?>
<AssignMessage async="false" continueOnError="false" enabled="true" name="Assign-Token-Details">
    <DisplayName>AssignMessage Token Details</DisplayName>
    <FaultRules/>
    <Properties/>
    <AssignVariable>
        <Name>requestId</Name>
        <Ref>accesstoken.RequestId</Ref>
    </AssignVariable>
    <IgnoreUnresolvedVariables>true</IgnoreUnresolvedVariables>
    <AssignTo type="request" transport="http" createNew="false"/>
</AssignMessage>