<?xml version="1.0" encoding="UTF-8" standalone="yes"?>
<RaiseFault async="false" continueOnError="false" enabled="true" name="Fault.InvalidAccessToken">
    <DisplayName>Fault.InvalidAccessToken</DisplayName>
    <FaultRules/>
    <Properties/>
    <FaultResponse>
        <Set>
            <Payload contentType="application/json" variablePrefix="@" variableSuffix="#">
                {
                "status": 401,
                "message": "Unauthorized",
                "description": "Invalid access token",
                "code": 10009,
                "more_info": "http://www.example.com/codes/10009"
                }
            </Payload>
            <StatusCode>401</StatusCode>
            <ReasonPhrase>Unauthorized</ReasonPhrase>
        </Set>
    </FaultResponse>
    <IgnoreUnresolvedVariables>true</IgnoreUnresolvedVariables>
</RaiseFault>